openai_kira/Chat/Optimizer.py
openai_kira/Chat/__init__.py
openai_kira/Chat/module/__init__.py
openai_kira/Chat/module/main.py
openai_kira/Chat/module/platform.py
openai_kira/Chat/module/plugin/__init__.py
openai_kira/Chat/module/plugin/_plugin_tool.py
openai_kira/Chat/module/plugin/_zhihu.py
openai_kira/Chat/module/plugin/details.py
openai_kira/Chat/module/plugin/duckgo.py
openai_kira/Chat/module/plugin/search.py
openai_kira/Chat/module/plugin/time.py
openai_kira/Chat/module/plugin/week.py
openai_kira/Chat/pot.py
openai_kira/Chat/test_module.py
openai_kira/Chat/text_analysis_tools/LICENSE
openai_kira/Chat/text_analysis_tools/README.md
openai_kira/Chat/text_analysis_tools/__init__.py
openai_kira/Chat/text_analysis_tools/api/data/apple.png
openai_kira/Chat/text_analysis_tools/api/data/map.png
openai_kira/Chat/text_analysis_tools/api/data/simfang.ttf
openai_kira/Chat/text_analysis_tools/api/data/stop_words.txt
openai_kira/Chat/text_analysis_tools/api/data/synonym.json
openai_kira/Chat/text_analysis_tools/api/keyphrase/__init__.py
openai_kira/Chat/text_analysis_tools/api/keyphrase/keyphrase.py
openai_kira/Chat/text_analysis_tools/api/keywords/__init__.py
openai_kira/Chat/text_analysis_tools/api/keywords/textrank.py
openai_kira/Chat/text_analysis_tools/api/keywords/tfidf.py
openai_kira/Chat/text_analysis_tools/api/sentiment/__init__.py
openai_kira/Chat/text_analysis_tools/api/sentiment/data/degreeDict.json
openai_kira/Chat/text_analysis_tools/api/sentiment/data/jieba.dic
openai_kira/Chat/text_analysis_tools/api/sentiment/data/notDict.json
openai_kira/Chat/text_analysis_tools/api/sentiment/data/sentimentDict.json
openai_kira/Chat/text_analysis_tools/api/sentiment/data/stopwords.txt.json
openai_kira/Chat/text_analysis_tools/api/sentiment/sentiment.py
openai_kira/Chat/text_analysis_tools/api/summarization/__init__.py
openai_kira/Chat/text_analysis_tools/api/summarization/textrank_summarization.py
openai_kira-0.3.6.dist-info/WHEEL
openai_kira-0.3.6.dist-info/LICENSE
openai_kira-0.3.6.dist-info/METADATA
openai_kira-0.3.6.dist-info/RECORD
